{
  "project_info": {
    "project_number": "244500879472",
    "project_id": "quizo-6b53e",
    "storage_bucket": "quizo-6b53e.appspot.com"
  },
  "client": [
    {
      "client_info": {
        "mobilesdk_app_id": "1:244500879472:android:eae17d63be3a00b20ebcb5",
        "android_client_info": {
          "package_name": "com.example.quiz"
        }
      },
      "oauth_client": [
        {
          "client_id": "244500879472-rikuslqlnuviocad3ci766ufsoe215he.apps.googleusercontent.com",
          "client_type": 3
        }
      ],
      "api_key": [
        {
          "current_key": "AIzaSyDxzr3y_TgbRrr0rmkbYXZG8dMlne17tfQ"
        }
      ],
      "services": {
        "appinvite_service": {
          "other_platform_oauth_client": [
            {
              "client_id": "244500879472-rikuslqlnuviocad3ci766ufsoe215he.apps.googleusercontent.com",
              "client_type": 3
            }
          ]
        }
      }
    }
  ],
  "configuration_version": "1"
}